MANIFEST.in
setup.py
src/asm/__init__.py
src/asm.translation.egg-info/PKG-INFO
src/asm.translation.egg-info/SOURCES.txt
src/asm.translation.egg-info/dependency_links.txt
src/asm.translation.egg-info/not-zip-safe
src/asm.translation.egg-info/requires.txt
src/asm.translation.egg-info/top_level.txt
src/asm/translation/__init__.py
src/asm/translation/configure.zcml
src/asm/translation/interfaces.py
src/asm/translation/translation.py
src/asm/translation/tests/__init__.py
src/asm/translation/tests/ftesting.zcml
src/asm/translation/tests/test_translation.py
src/asm/translation/translation_templates/translationmenu.pt