Metadata-Version: 1.0
Name: asm.translation
Version: 0.1.9
Summary: Multi-lingual content for Assembly CMS
Home-page: UNKNOWN
Author: Webcrew
Author-email: web@assembly.org
License: proprietary
Platform: UNKNOWN
